alchemy_mapper/__init__.py
alchemy_mapper/mapper.py
alchemy_mapper-0.1.1.dist-info/METADATA
alchemy_mapper-0.1.1.dist-info/WHEEL
alchemy_mapper-0.1.1.dist-info/RECORD
