Metadata-Version: 2.4
Name: alchemy-mapper
Version: 0.1.1
Summary: Async SQLAlchemy Core to Pydantic mapper for CQRS read-side queries
Project-URL: Homepage, https://github.com/yourusername/alchemy-mapper
Project-URL: Documentation, https://github.com/yourusername/alchemy-mapper#readme
Project-URL: Repository, https://github.com/yourusername/alchemy-mapper
Project-URL: Issues, https://github.com/yourusername/alchemy-mapper/issues
Author: AlchemyMapper Contributors
License: MIT
Keywords: async,cqrs,database,mapper,pydantic,query,sqlalchemy
Classifier: Development Status :: 4 - Beta
Classifier: Intended Audience :: Developers
Classifier: License :: OSI Approved :: MIT License
Classifier: Programming Language :: Python :: 3
Classifier: Programming Language :: Python :: 3.13
Classifier: Topic :: Database
Classifier: Topic :: Software Development :: Libraries :: Python Modules
Requires-Python: >=3.13
Requires-Dist: pydantic>=2.0
Requires-Dist: sqlalchemy[asyncio]>=2.0
